uthavu_utils/__init__.py
uthavu_utils/format_date.py
uthavu_utils-0.0.1.dist-info/METADATA
uthavu_utils-0.0.1.dist-info/WHEEL
uthavu_utils-0.0.1.dist-info/top_level.txt
uthavu_utils-0.0.1.dist-info/RECORD
